choppera/__init__.py
choppera/chopper.py
choppera/config.py
choppera/flightpaths.py
choppera/frequencies.py
choppera/nexus.py
choppera/phase.py
choppera/primary.py
choppera/secondary.py
choppera/tv_patch.py
choppera/utils.py
choppera-0.1.6.dist-info/METADATA
choppera-0.1.6.dist-info/WHEEL
choppera-0.1.6.dist-info/licenses/LICENSE.txt
choppera-0.1.6.dist-info/RECORD
