Metadata-Version: 2.4
Name: choppera
Version: 0.1.6
Summary: Chopper inverse velocity transport
Project-URL: Documentation, https://github.com/g5t/choppera#readme
Project-URL: Issues, https://github.com/g5t/choppera/issues
Project-URL: Source, https://github.com/g5t/choppera
Author-email: Gregory Tucker <gregory.tucker@ess.eu>
License-Expression: BSD-3-Clause
License-File: LICENSE.txt
Classifier: Development Status :: 4 - Beta
Classifier: Programming Language :: Python
Classifier: Programming Language :: Python :: 3.10
Classifier: Programming Language :: Python :: 3.11
Classifier: Programming Language :: Python :: 3.12
Classifier: Programming Language :: Python :: 3.13
Classifier: Programming Language :: Python :: Implementation :: CPython
Classifier: Programming Language :: Python :: Implementation :: PyPy
Requires-Python: >=3.10
Requires-Dist: numpy>=2.0
Requires-Dist: polystar>=0.4.4
Requires-Dist: scipp>=25.1
Requires-Dist: scippnexus>=24.8
Requires-Dist: scipy>=1.7.0
Requires-Dist: strictyaml>=1.7
